sheets_manager/__init__.py
sheets_manager/sheets_manager.py
spreadsheet_manager-0.0.2.dist-info/LICENSE
spreadsheet_manager-0.0.2.dist-info/METADATA
spreadsheet_manager-0.0.2.dist-info/WHEEL
spreadsheet_manager-0.0.2.dist-info/top_level.txt
spreadsheet_manager-0.0.2.dist-info/RECORD
