Metadata-Version: 2.1
Name: spreadsheet-manager
Version: 0.0.2
Summary: A Python package to load and manage Google Sheets or Excel file data.
Author: Yan Sido
Author-email: yansido1@gmail.com
Keywords: python,google-sheets,excel,spreadsheet,spreadsheet manager,google sheets loader,excel loader
Classifier: Development Status :: 3 - Alpha
Classifier: Intended Audience :: Developers
Classifier: Programming Language :: Python :: 3
Classifier: Operating System :: Unix
Classifier: Operating System :: MacOS :: MacOS X
Classifier: Operating System :: Microsoft :: Windows
License-File: LICENSE
Requires-Dist: pandas==2.0.2
